donald_maga/__init__.py
donald_maga/maga.py
donald_maga-1.45.dist-info/METADATA
donald_maga-1.45.dist-info/WHEEL
donald_maga-1.45.dist-info/top_level.txt
donald_maga-1.45.dist-info/RECORD
