Metadata-Version: 2.4
Name: donald-maga
Version: 1.45
Summary: MAGA! WIN!
Author: Luxun
Author-email: 
Classifier: Programming Language :: Python :: 3
Classifier: License :: OSI Approved :: MIT License
Classifier: Operating System :: OS Independent
Dynamic: author
Dynamic: classifier
Dynamic: description
Dynamic: description-content-type
Dynamic: summary
